{
	"ImportPath": "github.com/dooman87/transformimgs",
	"GoVersion": "go1.7",
	"GodepVersion": "v79",
	"Packages": [
		"./..."
	],
	"Deps": [
		{
			"ImportPath": "github.com/dooman87/kolibri/health",
			"Rev": "c194ff118b679de1f8ace1a8104b243c14e9562b"
		},
		{
			"ImportPath": "github.com/dooman87/kolibri/test",
			"Rev": "c194ff118b679de1f8ace1a8104b243c14e9562b"
		},
		{
			"ImportPath": "github.com/gorilla/mux",
			"Comment": "v1.3.0",
			"Rev": "392c28fe23e1c45ddba891b0320b3b5df220beea"
		},
		{
			"ImportPath": "github.com/pkg/errors",
			"Comment": "v0.7.1",
			"Rev": "17b591df37844cde689f4d5813e5cea0927d8dd2"
		}
	]
}
